postschema/__init__.py
postschema/actor.py
postschema/alembic.ini
postschema/commons.py
postschema/contrib.py
postschema/core.py
postschema/decorators.py
postschema/exceptions.py
postschema/fields.py
postschema/hooks.py
postschema/logging.py
postschema/middlewares.py
postschema/provision_db.py
postschema/schema.py
postschema/scope.py
postschema/sentry.py
postschema/shield.py
postschema/spec.py
postschema/utils.py
postschema/validators.py
postschema/view.py
postschema/view_bases.py
postschema/workspace.py
postschema/alembic/env.py
postschema/alembic/script.py.mako
postschema/auth/clauses.py
postschema/auth/context.py
postschema/auth/perms.py
postschema/auth/templates/redoc.html
postschema/auth/templates/set_new_password.html
postschema/sql/functions/id_constraint.sql
postschema/sql/functions/jsonb_merge.sql
postschema/sql/queries/list_members.sql
postschema-0.17.31.dist-info/LICENSE
postschema-0.17.31.dist-info/METADATA
postschema-0.17.31.dist-info/WHEEL
postschema-0.17.31.dist-info/top_level.txt
postschema-0.17.31.dist-info/RECORD
